tsih/.__init__.py.~undo-tree~
tsih/__init__.py
tsih/serialization.py
tsih/utils.py
tsih-0.1.9.dist-info/LICENSE
tsih-0.1.9.dist-info/METADATA
tsih-0.1.9.dist-info/WHEEL
tsih-0.1.9.dist-info/top_level.txt
tsih-0.1.9.dist-info/RECORD
