Metadata-Version: 2.1
Name: tsih
Version: 0.1.9
Summary: A lightweight library to store an object's history into a SQL database
Home-page: https://github.com/balkian/tsih
Author: J. Fernando Sanchez
Author-email: jf.sanchez@upm.es
License: UNKNOWN
Download-URL: https://github.com/balkian/tsih/archive/0.1.9.tar.gz
Keywords: history,sql,records
Platform: UNKNOWN
Classifier: Development Status :: 4 - Beta
Classifier: Environment :: Console
Classifier: Intended Audience :: Developers
Classifier: License :: OSI Approved :: Apache Software License
Classifier: Operating System :: MacOS :: MacOS X
Classifier: Operating System :: Microsoft :: Windows
Classifier: Operating System :: POSIX
Classifier: Programming Language :: Python :: 3
Provides-Extra: all
